peachpayments_partner_pydantic/__init__.py
peachpayments_partner_pydantic/exception_handlers.py
peachpayments_partner_pydantic/helpers.py
peachpayments_partner_pydantic/inbound_schemas.py
peachpayments_partner_pydantic/outbound_schemas.py
peachpayments_partner_pydantic/schemas.py
peachpayments_partner_pydantic-1.2.0.dist-info/LICENSE.txt
peachpayments_partner_pydantic-1.2.0.dist-info/METADATA
peachpayments_partner_pydantic-1.2.0.dist-info/WHEEL
peachpayments_partner_pydantic-1.2.0.dist-info/RECORD
