Metadata-Version: 2.1
Name: peachpayments-partner-pydantic
Version: 1.2.0
Summary: PeachPayments Partner Pydantic library contains Pydantic schemas to help integrate PeachPayments with their partners.
Home-page: https://gitlab.com/peachpayments/peachpayments-partner-pydantic/
License: MIT
Author: PeachPayments
Author-email: support@peachpayments.com
Requires-Python: >=3.9,<4.0
Classifier: Development Status :: 4 - Beta
Classifier: Intended Audience :: Developers
Classifier: Intended Audience :: Financial and Insurance Industry
Classifier: License :: OSI Approved :: MIT License
Classifier: Operating System :: OS Independent
Classifier: Programming Language :: Python :: 3
Classifier: Programming Language :: Python :: 3.9
Classifier: Programming Language :: Python :: 3.10
Classifier: Programming Language :: Python :: 3.11
Classifier: Topic :: Software Development :: Libraries :: Python Modules
Classifier: Topic :: Utilities
Classifier: Typing :: Typed
Requires-Dist: email-validator (>=1.2.1,<2.0.0)
Requires-Dist: ipaddress (>=1.0.23,<2.0.0)
Requires-Dist: iso4217 (>=1.9.20220401,<2.0.0)
Requires-Dist: peachpayments-partner (>=0.1.12,<0.2.0)
Requires-Dist: pydantic (>=1.9.1,<2.0.0)
Project-URL: Repository, https://gitlab.com/peachpayments/peachpayments-partner-pydantic/
